{
  "parent": "minecraft:recipes/root",
  "criteria": {
    "has_the_recipe": {
      "conditions": {
        "recipe": "uselessmod:super_useless_bars"
      },
      "trigger": "minecraft:recipe_unlocked"
    },
    "has_useless_ingot": {
      "conditions": {
        "items": [
          {
            "items": "#forge:ingots/super_useless"
          }
        ]
      },
      "trigger": "minecraft:inventory_changed"
    }
  },
  "requirements": [
    [
      "has_the_recipe",
      "has_useless_ingot"
    ]
  ],
  "rewards": {
    "recipes": [
      "uselessmod:super_useless_bars"
    ]
  }
}